COPYRIGHT
MANIFEST.in
Makefile
README
setup.py
test/__init__.py
test/__init__.pyc
test/test_basics.py
test/test_compile.py
test/__pycache__/test_basics.cpython-27-PYTEST.pyc
test/__pycache__/test_compile.cpython-27-PYTEST.pyc
tiddlywebplugins/__init__.py
tiddlywebplugins/extraclude.py
tiddlywebplugins.extraclude.egg-info/PKG-INFO
tiddlywebplugins.extraclude.egg-info/SOURCES.txt
tiddlywebplugins.extraclude.egg-info/dependency_links.txt
tiddlywebplugins.extraclude.egg-info/namespace_packages.txt
tiddlywebplugins.extraclude.egg-info/not-zip-safe
tiddlywebplugins.extraclude.egg-info/requires.txt
tiddlywebplugins.extraclude.egg-info/top_level.txt