Metadata-Version: 1.0
Name: tiddlywebplugins.extraclude
Version: 0.1
Summary: Automatic handling of extraclude on tiddler PUT
Home-page: http://pypi.python.org/pypi/tiddlywebplugins.extraclude
Author: Chris Dent
Author-email: cdent@peermore.com
License: UNKNOWN
Platform: Posix; MacOS X; Windows
